text_ppf/__init__.py
text_ppf/text_ppf.py
text_ppf-1.0.0.dist-info/LICENSE
text_ppf-1.0.0.dist-info/METADATA
text_ppf-1.0.0.dist-info/WHEEL
text_ppf-1.0.0.dist-info/top_level.txt
text_ppf-1.0.0.dist-info/RECORD
