Metadata-Version: 2.1
Name: text-ppf
Version: 1.0.0
Summary: Text pre-processing function for NLP
Home-page: https://github.com/Mandy-cyber/TextPreProcessing
Author: MandyCyber
Author-email: 
License: UNKNOWN
Platform: UNKNOWN
Classifier: Programming Language :: Python :: 3
Classifier: License :: OSI Approved :: MIT License
Classifier: Operating System :: OS Independent
Requires-Python: >=3.6
License-File: LICENSE
Requires-Dist: tensorflow
Requires-Dist: string
Requires-Dist: re
Requires-Dist: nltk
